hybracter/__init__.py
hybracter/__main__.py
hybracter/concat_GFAs_hybracter.py
hybracter/hybracter.CITATION
hybracter/hybracter.LICENSE
hybracter/hybracter.VERSION
hybracter/util.py
hybracter/config/config.yaml
hybracter/contaminant_genomes/lambda.fasta
hybracter/test_data/test_hybrid_input.csv
hybracter/test_data/test_hybrid_input_auto.csv
hybracter/test_data/test_hybrid_input_datadir.csv
hybracter/test_data/test_hybrid_input_low_illumina_coverage.csv
hybracter/test_data/test_hybrid_input_not_gzipped.csv
hybracter/test_data/test_hybrid_input_ultra_low_illumina_coverage.csv
hybracter/test_data/test_long_input.csv
hybracter/test_data/test_long_input_auto.csv
hybracter/test_data/test_long_input_datadir.csv
hybracter/test_data/Fastqs/C222_plasmid.fasta
hybracter/test_data/Fastqs/assembly.fasta
hybracter/test_data/Fastqs/generating_simulated_reads.sh
hybracter/test_data/Fastqs/test_long_reads.fastq
hybracter/test_data/Fastqs/test_long_reads.fastq.gz
hybracter/test_data/Fastqs/test_long_reads_subsampled.fastq.gz
hybracter/test_data/Fastqs/test_short_reads_R1.fastq.gz
hybracter/test_data/Fastqs/test_short_reads_R2.fastq.gz
hybracter/test_data/Fastqs/test_short_reads_low_depth_R1.fastq
hybracter/test_data/Fastqs/test_short_reads_low_depth_R1.fastq.gz
hybracter/test_data/Fastqs/test_short_reads_low_depth_R2.fastq
hybracter/test_data/Fastqs/test_short_reads_low_depth_R2.fastq.gz
hybracter/test_data/Fastqs/test_short_reads_ultra_low_depth_R1.fastq.gz
hybracter/test_data/Fastqs/test_short_reads_ultra_low_depth_R2.fastq.gz
hybracter/test_data/Plassembler_DB_Test/plsdb.fasta
hybracter/test_data/Plassembler_DB_Test/plsdb_2023_11_03_v2.msh
hybracter/test_data/Plassembler_DB_Test/plsdb_2023_11_03_v2.tsv
hybracter/test_data/dnaapler_custom_db/all.faa
hybracter/workflow/hybrid.smk
hybracter/workflow/install.smk
hybracter/workflow/long.smk
hybracter/workflow/test_hybrid.smk
hybracter/workflow/test_long.smk
hybracter/workflow/envs/ale.yaml
hybracter/workflow/envs/bwa.yaml
hybracter-0.12.0.dist-info/licenses/LICENSE
hybracter-0.12.0.dist-info/METADATA
hybracter-0.12.0.dist-info/WHEEL
hybracter-0.12.0.dist-info/entry_points.txt
hybracter-0.12.0.dist-info/top_level.txt
hybracter-0.12.0.dist-info/RECORD
