Metadata-Version: 2.4
Name: hybracter
Version: 0.12.0
Summary: An automated long-read first bacterial genome assembly pipeline.
Home-page: https://github.com/gbouras13/hybracter
Author: George Bouras
Author-email: george.bouras@adelaide.edu.au
Requires-Python: >=3.9
License-File: LICENSE
Requires-Dist: snakemake>=7.14.0
Requires-Dist: pyyaml>=6.0
Requires-Dist: Click>=8.1.3
Requires-Dist: attrmap>=0.0.5
Requires-Dist: biopython>=1.76
Dynamic: author
Dynamic: author-email
Dynamic: description
Dynamic: description-content-type
Dynamic: home-page
Dynamic: license-file
Dynamic: requires-dist
Dynamic: requires-python
Dynamic: summary
